Compiled from "com_unascribed_ears_Ears.java"
public class com_unascribed_ears_Ears {
  private static final com_unascribed_ears_Ears INST;

  public static final java.util.Map<java.lang.String, com.unascribed.ears.api.features.EarsFeatures> earsSkinFeatures;

  public static net.minecraft.client.Minecraft game;

  private ds render;

  private float brightness;

  private float tickDelta;

  public static boolean forceBipedTextureHeight;

  public static ps slimLeftArm;

  public static ps slimRightArm;

  public static ps fatLeftArm;

  public static ps fatRightArm;

  private static final java.lang.reflect.Method rr_setAreaOpaque;

  private static final java.lang.reflect.Method rr_setAreaTransparent;

  private static final java.lang.reflect.Field rr_imageHeight;

  private static final java.lang.reflect.Field rr_imageWidth;

  private static final java.lang.reflect.Field rr_imageData;

  private static final java.lang.reflect.Field ps_vertices;

  private static final java.lang.reflect.Field ds_modelBipedMain;

  private static boolean forceTextureHeight;

  private static fh myModel;

  private final com.unascribed.ears.common.legacy.ImmediateEarsRenderDelegate<gs, ps> delegate;

  public com_unascribed_ears_Ears();
    Code:
       0: aload_0
       1: invokespecial #5                  // Method java/lang/Object."<init>":()V
       4: aload_0
       5: new           #6                  // class com_unascribed_ears_Ears$1
       8: dup
       9: aload_0
      10: invokespecial #7                  // Method com_unascribed_ears_Ears$1."<init>":(Lcom_unascribed_ears_Ears;)V
      13: putfield      #8                  // Field delegate:Lcom/unascribed/ears/common/legacy/ImmediateEarsRenderDelegate;
      16: return

  public static void init(net.minecraft.client.Minecraft);
    Code:
       0: aload_0
       1: putstatic     #9                  // Field game:Lnet/minecraft/client/Minecraft;
       4: getstatic     #10                 // Field com/unascribed/ears/common/debug/EarsLog.DEBUG:Z
       7: ifeq          22
      10: getstatic     #11                 // Field com/unascribed/ears/common/debug/EarsLog$Tag.PLATFORM:Lcom/unascribed/ears/common/debug/EarsLog$Tag;
      13: ldc           #12                 // String Initialized - Better Than Adventure
      15: iconst_0
      16: anewarray     #13                 // class java/lang/Object
      19: invokestatic  #14                 // Method com/unascribed/ears/common/debug/EarsLog.debugva:(Lcom/unascribed/ears/common/debug/EarsLog$Tag;Ljava/lang/String;[Ljava/lang/Object;)V
      22: return

  public static void postRenderSpecials(ds, gs, float);
    Code:
       0: getstatic     #15                 // Field INST:Lcom_unascribed_ears_Ears;
       3: aload_0
       4: aload_1
       5: fload_2
       6: invokevirtual #16                 // Method render:(Lds;Lgs;F)V
       9: return

  public static void postDrawFirstPersonHand(ds);
    Code:
       0: getstatic     #15                 // Field INST:Lcom_unascribed_ears_Ears;
       3: aload_0
       4: getstatic     #9                  // Field game:Lnet/minecraft/client/Minecraft;
       7: getfield      #17                 // Field net/minecraft/client/Minecraft.h:Ldc;
      10: fconst_0
      11: invokevirtual #18                 // Method renderRightArm:(Lds;Lgs;F)V
      14: return

  public static void preprocessSkin(rr, java.awt.image.BufferedImage, java.awt.image.BufferedImage);
    Code:
       0: getstatic     #19                 // Field com/unascribed/ears/common/debug/EarsLog$Tag.PLATFORM_INJECT:Lcom/unascribed/ears/common/debug/EarsLog$Tag;
       3: ldc           #20                 // String preprocessSkin({}, {}, {})
       5: aload_0
       6: aload_1
       7: aload_2
       8: invokestatic  #21                 // Method com/unascribed/ears/common/debug/EarsLog.debug:(Lcom/unascribed/ears/common/debug/EarsLog$Tag;Ljava/lang/String;Ljava/lang/Object;Ljava/lang/Object;Ljava/lang/Object;)V
      11: aload_2
      12: getstatic     #22                 // Field com/unascribed/ears/common/util/EarsStorage$Key.ALFALFA:Lcom/unascribed/ears/common/util/EarsStorage$Key;
      15: new           #23                 // class com/unascribed/ears/common/legacy/AWTEarsImage
      18: dup
      19: aload_1
      20: invokespecial #24                 // Method com/unascribed/ears/common/legacy/AWTEarsImage."<init>":(Ljava/awt/image/BufferedImage;)V
      23: invokestatic  #25                 // Method com/unascribed/ears/common/EarsCommon.preprocessSkin:(Lcom/unascribed/ears/common/WritableEarsImage;)Lcom/unascribed/ears/api/features/AlfalfaData;
      26: invokestatic  #26                 // Method com/unascribed/ears/common/util/EarsStorage.put:(Ljava/lang/Object;Lcom/unascribed/ears/common/util/EarsStorage$Key;Ljava/lang/Object;)V
      29: return

  public static java.awt.image.BufferedImage interceptParseUserSkin(rr, java.awt.image.BufferedImage);
    Code:
       0: getstatic     #19                 // Field com/unascribed/ears/common/debug/EarsLog$Tag.PLATFORM_INJECT:Lcom/unascribed/ears/common/debug/EarsLog$Tag;
       3: ldc           #27                 // String parseUserSkin({}, {})
       5: aload_0
       6: aload_1
       7: invokestatic  #28                 // Method com/unascribed/ears/common/debug/EarsLog.debug:(Lcom/unascribed/ears/common/debug/EarsLog$Tag;Ljava/lang/String;Ljava/lang/Object;Ljava/lang/Object;)V
      10: aload_1
      11: ifnonnull     24
      14: getstatic     #19                 // Field com/unascribed/ears/common/debug/EarsLog$Tag.PLATFORM_INJECT:Lcom/unascribed/ears/common/debug/EarsLog$Tag;
      17: ldc           #29                 // String parseUserSkin(...): Image is null
      19: invokestatic  #30                 // Method com/unascribed/ears/common/debug/EarsLog.debug:(Lcom/unascribed/ears/common/debug/EarsLog$Tag;Ljava/lang/String;)V
      22: aconst_null
      23: areturn
      24: aload_0
      25: bipush        64
      27: invokestatic  #31                 // Method setImageWidth:(Lrr;I)V
      30: aload_0
      31: bipush        64
      33: invokestatic  #32                 // Method setImageHeight:(Lrr;I)V
      36: new           #33                 // class java/awt/image/BufferedImage
      39: dup
      40: bipush        64
      42: bipush        64
      44: iconst_2
      45: invokespecial #34                 // Method java/awt/image/BufferedImage."<init>":(III)V
      48: astore_2
      49: aload_2
      50: invokevirtual #35                 // Method java/awt/image/BufferedImage.getGraphics:()Ljava/awt/Graphics;
      53: astore_3
      54: aload_3
      55: aload_1
      56: iconst_0
      57: iconst_0
      58: aconst_null
      59: invokevirtual #36                 // Method java/awt/Graphics.drawImage:(Ljava/awt/Image;IILjava/awt/image/ImageObserver;)Z
      62: pop
      63: aload_1
      64: invokevirtual #37                 // Method java/awt/image/BufferedImage.getHeight:()I
      67: bipush        32
      69: if_icmpne     352
      72: getstatic     #19                 // Field com/unascribed/ears/common/debug/EarsLog$Tag.PLATFORM_INJECT:Lcom/unascribed/ears/common/debug/EarsLog$Tag;
      75: ldc           #38                 // String parseUserSkin(...): Upgrading legacy skin
      77: invokestatic  #30                 // Method com/unascribed/ears/common/debug/EarsLog.debug:(Lcom/unascribed/ears/common/debug/EarsLog$Tag;Ljava/lang/String;)V
      80: aload_3
      81: aload_2
      82: bipush        24
      84: bipush        48
      86: bipush        20
      88: bipush        52
      90: iconst_4
      91: bipush        16
      93: bipush        8
      95: bipush        20
      97: aconst_null
      98: invokevirtual #39                 // Method java/awt/Graphics.drawImage:(Ljava/awt/Image;IIIIIIIILjava/awt/image/ImageObserver;)Z
     101: pop
     102: aload_3
     103: aload_2
     104: bipush        28
     106: bipush        48
     108: bipush        24
     110: bipush        52
     112: bipush        8
     114: bipush        16
     116: bipush        12
     118: bipush        20
     120: aconst_null
     121: invokevirtual #39                 // Method java/awt/Graphics.drawImage:(Ljava/awt/Image;IIIIIIIILjava/awt/image/ImageObserver;)Z
     124: pop
     125: aload_3
     126: aload_2
     127: bipush        20
     129: bipush        52
     131: bipush        16
     133: bipush        64
     135: bipush        8
     137: bipush        20
     139: bipush        12
     141: bipush        32
     143: aconst_null
     144: invokevirtual #39                 // Method java/awt/Graphics.drawImage:(Ljava/awt/Image;IIIIIIIILjava/awt/image/ImageObserver;)Z
     147: pop
     148: aload_3
     149: aload_2
     150: bipush        24
     152: bipush        52
     154: bipush        20
     156: bipush        64
     158: iconst_4
     159: bipush        20
     161: bipush        8
     163: bipush        32
     165: aconst_null
     166: invokevirtual #39                 // Method java/awt/Graphics.drawImage:(Ljava/awt/Image;IIIIIIIILjava/awt/image/ImageObserver;)Z
     169: pop
     170: aload_3
     171: aload_2
     172: bipush        28
     174: bipush        52
     176: bipush        24
     178: bipush        64
     180: iconst_0
     181: bipush        20
     183: iconst_4
     184: bipush        32
     186: aconst_null
     187: invokevirtual #39                 // Method java/awt/Graphics.drawImage:(Ljava/awt/Image;IIIIIIIILjava/awt/image/ImageObserver;)Z
     190: pop
     191: aload_3
     192: aload_2
     193: bipush        32
     195: bipush        52
     197: bipush        28
     199: bipush        64
     201: bipush        12
     203: bipush        20
     205: bipush        16
     207: bipush        32
     209: aconst_null
     210: invokevirtual #39                 // Method java/awt/Graphics.drawImage:(Ljava/awt/Image;IIIIIIIILjava/awt/image/ImageObserver;)Z
     213: pop
     214: aload_3
     215: aload_2
     216: bipush        40
     218: bipush        48
     220: bipush        36
     222: bipush        52
     224: bipush        44
     226: bipush        16
     228: bipush        48
     230: bipush        20
     232: aconst_null
     233: invokevirtual #39                 // Method java/awt/Graphics.drawImage:(Ljava/awt/Image;IIIIIIIILjava/awt/image/ImageObserver;)Z
     236: pop
     237: aload_3
     238: aload_2
     239: bipush        44
     241: bipush        48
     243: bipush        40
     245: bipush        52
     247: bipush        48
     249: bipush        16
     251: bipush        52
     253: bipush        20
     255: aconst_null
     256: invokevirtual #39                 // Method java/awt/Graphics.drawImage:(Ljava/awt/Image;IIIIIIIILjava/awt/image/ImageObserver;)Z
     259: pop
     260: aload_3
     261: aload_2
     262: bipush        36
     264: bipush        52
     266: bipush        32
     268: bipush        64
     270: bipush        48
     272: bipush        20
     274: bipush        52
     276: bipush        32
     278: aconst_null
     279: invokevirtual #39                 // Method java/awt/Graphics.drawImage:(Ljava/awt/Image;IIIIIIIILjava/awt/image/ImageObserver;)Z
     282: pop
     283: aload_3
     284: aload_2
     285: bipush        40
     287: bipush        52
     289: bipush        36
     291: bipush        64
     293: bipush        44
     295: bipush        20
     297: bipush        48
     299: bipush        32
     301: aconst_null
     302: invokevirtual #39                 // Method java/awt/Graphics.drawImage:(Ljava/awt/Image;IIIIIIIILjava/awt/image/ImageObserver;)Z
     305: pop
     306: aload_3
     307: aload_2
     308: bipush        44
     310: bipush        52
     312: bipush        40
     314: bipush        64
     316: bipush        40
     318: bipush        20
     320: bipush        44
     322: bipush        32
     324: aconst_null
     325: invokevirtual #39                 // Method java/awt/Graphics.drawImage:(Ljava/awt/Image;IIIIIIIILjava/awt/image/ImageObserver;)Z
     328: pop
     329: aload_3
     330: aload_2
     331: bipush        48
     333: bipush        52
     335: bipush        44
     337: bipush        64
     339: bipush        52
     341: bipush        20
     343: bipush        56
     345: bipush        32
     347: aconst_null
     348: invokevirtual #39                 // Method java/awt/Graphics.drawImage:(Ljava/awt/Image;IIIIIIIILjava/awt/image/ImageObserver;)Z
     351: pop
     352: aload_3
     353: invokevirtual #40                 // Method java/awt/Graphics.dispose:()V
     356: aload_2
     357: getstatic     #22                 // Field com/unascribed/ears/common/util/EarsStorage$Key.ALFALFA:Lcom/unascribed/ears/common/util/EarsStorage$Key;
     360: new           #23                 // class com/unascribed/ears/common/legacy/AWTEarsImage
     363: dup
     364: aload_2
     365: invokespecial #24                 // Method com/unascribed/ears/common/legacy/AWTEarsImage."<init>":(Ljava/awt/image/BufferedImage;)V
     368: invokestatic  #25                 // Method com/unascribed/ears/common/EarsCommon.preprocessSkin:(Lcom/unascribed/ears/common/WritableEarsImage;)Lcom/unascribed/ears/api/features/AlfalfaData;
     371: invokestatic  #26                 // Method com/unascribed/ears/common/util/EarsStorage.put:(Ljava/lang/Object;Lcom/unascribed/ears/common/util/EarsStorage$Key;Ljava/lang/Object;)V
     374: aload_0
     375: aload_2
     376: invokevirtual #41                 // Method java/awt/image/BufferedImage.getRaster:()Ljava/awt/image/WritableRaster;
     379: invokevirtual #42                 // Method java/awt/image/WritableRaster.getDataBuffer:()Ljava/awt/image/DataBuffer;
     382: checkcast     #43                 // class java/awt/image/DataBufferInt
     385: invokevirtual #44                 // Method java/awt/image/DataBufferInt.getData:()[I
     388: invokestatic  #45                 // Method setImageData:(Lrr;[I)V
     391: aload_0
     392: invokedynamic #46,  0             // InvokeDynamic #0:stripAlpha:(Lrr;)Lcom/unascribed/ears/common/EarsCommon$StripAlphaMethod;
     397: iconst_1
     398: invokestatic  #47                 // Method com/unascribed/ears/common/EarsCommon.carefullyStripAlpha:(Lcom/unascribed/ears/common/EarsCommon$StripAlphaMethod;Z)V
     401: aload_0
     402: bipush        32
     404: iconst_0
     405: bipush        64
     407: bipush        32
     409: invokestatic  #48                 // Method setAreaTransparent:(Lrr;IIII)V
     412: aload_0
     413: iconst_0
     414: bipush        32
     416: bipush        16
     418: bipush        48
     420: invokestatic  #48                 // Method setAreaTransparent:(Lrr;IIII)V
     423: aload_0
     424: bipush        16
     426: bipush        32
     428: bipush        40
     430: bipush        48
     432: invokestatic  #48                 // Method setAreaTransparent:(Lrr;IIII)V
     435: aload_0
     436: bipush        40
     438: bipush        32
     440: bipush        56
     442: bipush        48
     444: invokestatic  #48                 // Method setAreaTransparent:(Lrr;IIII)V
     447: aload_0
     448: iconst_0
     449: bipush        48
     451: bipush        16
     453: bipush        64
     455: invokestatic  #48                 // Method setAreaTransparent:(Lrr;IIII)V
     458: aload_0
     459: bipush        48
     461: bipush        48
     463: bipush        64
     465: bipush        64
     467: invokestatic  #48                 // Method setAreaTransparent:(Lrr;IIII)V
     470: aload_2
     471: areturn

  private static void setImageWidth(rr, int);
    Code:
       0: getstatic     #49                 // Field rr_imageWidth:Ljava/lang/reflect/Field;
       3: aload_0
       4: iload_1
       5: invokestatic  #50                 // Method java/lang/Integer.valueOf:(I)Ljava/lang/Integer;
       8: invokevirtual #51                 // Method java/lang/reflect/Field.set:(Ljava/lang/Object;Ljava/lang/Object;)V
      11: goto          36
      14: astore_2
      15: aload_2
      16: instanceof    #53                 // class java/lang/RuntimeException
      19: ifeq          27
      22: aload_2
      23: checkcast     #53                 // class java/lang/RuntimeException
      26: athrow
      27: new           #53                 // class java/lang/RuntimeException
      30: dup
      31: aload_2
      32: invokespecial #54                 // Method java/lang/RuntimeException."<init>":(Ljava/lang/Throwable;)V
      35: athrow
      36: return
    Exception table:
       from    to  target type
           0    11    14   Class java/lang/Throwable

  private static void setImageHeight(rr, int);
    Code:
       0: getstatic     #55                 // Field rr_imageHeight:Ljava/lang/reflect/Field;
       3: aload_0
       4: iload_1
       5: invokestatic  #50                 // Method java/lang/Integer.valueOf:(I)Ljava/lang/Integer;
       8: invokevirtual #51                 // Method java/lang/reflect/Field.set:(Ljava/lang/Object;Ljava/lang/Object;)V
      11: goto          36
      14: astore_2
      15: aload_2
      16: instanceof    #53                 // class java/lang/RuntimeException
      19: ifeq          27
      22: aload_2
      23: checkcast     #53                 // class java/lang/RuntimeException
      26: athrow
      27: new           #53                 // class java/lang/RuntimeException
      30: dup
      31: aload_2
      32: invokespecial #54                 // Method java/lang/RuntimeException."<init>":(Ljava/lang/Throwable;)V
      35: athrow
      36: return
    Exception table:
       from    to  target type
           0    11    14   Class java/lang/Throwable

  private static void setImageData(rr, int[]);
    Code:
       0: getstatic     #56                 // Field rr_imageData:Ljava/lang/reflect/Field;
       3: aload_0
       4: aload_1
       5: invokevirtual #51                 // Method java/lang/reflect/Field.set:(Ljava/lang/Object;Ljava/lang/Object;)V
       8: goto          33
      11: astore_2
      12: aload_2
      13: instanceof    #53                 // class java/lang/RuntimeException
      16: ifeq          24
      19: aload_2
      20: checkcast     #53                 // class java/lang/RuntimeException
      23: athrow
      24: new           #53                 // class java/lang/RuntimeException
      27: dup
      28: aload_2
      29: invokespecial #54                 // Method java/lang/RuntimeException."<init>":(Ljava/lang/Throwable;)V
      32: athrow
      33: return
    Exception table:
       from    to  target type
           0     8    11   Class java/lang/Throwable

  private static void setAreaOpaque(rr, int, int, int, int);
    Code:
       0: getstatic     #19                 // Field com/unascribed/ears/common/debug/EarsLog$Tag.PLATFORM_INJECT:Lcom/unascribed/ears/common/debug/EarsLog$Tag;
       3: ldc           #57                 // String stripAlpha({}, {}, {}, {}, {})
       5: aload_0
       6: iload_1
       7: iload_2
       8: iload_3
       9: iload         4
      11: invokestatic  #58                 // Method com/unascribed/ears/common/debug/EarsLog.debug:(Lcom/unascribed/ears/common/debug/EarsLog$Tag;Ljava/lang/String;Ljava/lang/Object;IIII)V
      14: getstatic     #59                 // Field rr_setAreaOpaque:Ljava/lang/reflect/Method;
      17: aload_0
      18: iconst_4
      19: anewarray     #13                 // class java/lang/Object
      22: dup
      23: iconst_0
      24: iload_1
      25: invokestatic  #50                 // Method java/lang/Integer.valueOf:(I)Ljava/lang/Integer;
      28: aastore
      29: dup
      30: iconst_1
      31: iload_2
      32: invokestatic  #50                 // Method java/lang/Integer.valueOf:(I)Ljava/lang/Integer;
      35: aastore
      36: dup
      37: iconst_2
      38: iload_3
      39: invokestatic  #50                 // Method java/lang/Integer.valueOf:(I)Ljava/lang/Integer;
      42: aastore
      43: dup
      44: iconst_3
      45: iload         4
      47: invokestatic  #50                 // Method java/lang/Integer.valueOf:(I)Ljava/lang/Integer;
      50: aastore
      51: invokevirtual #60                 // Method java/lang/reflect/Method.invoke:(Ljava/lang/Object;[Ljava/lang/Object;)Ljava/lang/Object;
      54: pop
      55: goto          84
      58: astore        5
      60: aload         5
      62: instanceof    #53                 // class java/lang/RuntimeException
      65: ifeq          74
      68: aload         5
      70: checkcast     #53                 // class java/lang/RuntimeException
      73: athrow
      74: new           #53                 // class java/lang/RuntimeException
      77: dup
      78: aload         5
      80: invokespecial #54                 // Method java/lang/RuntimeException."<init>":(Ljava/lang/Throwable;)V
      83: athrow
      84: return
    Exception table:
       from    to  target type
           0    55    58   Class java/lang/Throwable

  private static void setAreaTransparent(rr, int, int, int, int);
    Code:
       0: getstatic     #61                 // Field rr_setAreaTransparent:Ljava/lang/reflect/Method;
       3: aload_0
       4: iconst_4
       5: anewarray     #13                 // class java/lang/Object
       8: dup
       9: iconst_0
      10: iload_1
      11: invokestatic  #50                 // Method java/lang/Integer.valueOf:(I)Ljava/lang/Integer;
      14: aastore
      15: dup
      16: iconst_1
      17: iload_2
      18: invokestatic  #50                 // Method java/lang/Integer.valueOf:(I)Ljava/lang/Integer;
      21: aastore
      22: dup
      23: iconst_2
      24: iload_3
      25: invokestatic  #50                 // Method java/lang/Integer.valueOf:(I)Ljava/lang/Integer;
      28: aastore
      29: dup
      30: iconst_3
      31: iload         4
      33: invokestatic  #50                 // Method java/lang/Integer.valueOf:(I)Ljava/lang/Integer;
      36: aastore
      37: invokevirtual #60                 // Method java/lang/reflect/Method.invoke:(Ljava/lang/Object;[Ljava/lang/Object;)Ljava/lang/Object;
      40: pop
      41: goto          70
      44: astore        5
      46: aload         5
      48: instanceof    #53                 // class java/lang/RuntimeException
      51: ifeq          60
      54: aload         5
      56: checkcast     #53                 // class java/lang/RuntimeException
      59: athrow
      60: new           #53                 // class java/lang/RuntimeException
      63: dup
      64: aload         5
      66: invokespecial #54                 // Method java/lang/RuntimeException."<init>":(Ljava/lang/Throwable;)V
      69: athrow
      70: return
    Exception table:
       from    to  target type
           0    41    44   Class java/lang/Throwable

  private static ib[] getVertices(ps);
    Code:
       0: getstatic     #62                 // Field ps_vertices:Ljava/lang/reflect/Field;
       3: aload_0
       4: invokevirtual #63                 // Method java/lang/reflect/Field.get:(Ljava/lang/Object;)Ljava/lang/Object;
       7: checkcast     #64                 // class "[Lib;"
      10: areturn
      11: astore_1
      12: new           #53                 // class java/lang/RuntimeException
      15: dup
      16: aload_1
      17: invokespecial #54                 // Method java/lang/RuntimeException."<init>":(Ljava/lang/Throwable;)V
      20: athrow
    Exception table:
       from    to  target type
           0    10    11   Class java/lang/Throwable

  private static fh getModelBipedMain(ds);
    Code:
       0: getstatic     #65                 // Field ds_modelBipedMain:Ljava/lang/reflect/Field;
       3: aload_0
       4: invokevirtual #63                 // Method java/lang/reflect/Field.get:(Ljava/lang/Object;)Ljava/lang/Object;
       7: checkcast     #66                 // class fh
      10: areturn
      11: astore_1
      12: new           #53                 // class java/lang/RuntimeException
      15: dup
      16: aload_1
      17: invokespecial #54                 // Method java/lang/RuntimeException."<init>":(Ljava/lang/Throwable;)V
      20: athrow
    Exception table:
       from    to  target type
           0    10    11   Class java/lang/Throwable

  private static void setModelBipedMain(ds, fh);
    Code:
       0: getstatic     #65                 // Field ds_modelBipedMain:Ljava/lang/reflect/Field;
       3: aload_0
       4: aload_1
       5: invokevirtual #51                 // Method java/lang/reflect/Field.set:(Ljava/lang/Object;Ljava/lang/Object;)V
       8: goto          21
      11: astore_2
      12: new           #53                 // class java/lang/RuntimeException
      15: dup
      16: aload_2
      17: invokespecial #54                 // Method java/lang/RuntimeException."<init>":(Ljava/lang/Throwable;)V
      20: athrow
      21: return
    Exception table:
       from    to  target type
           0     8    11   Class java/lang/Throwable

  public static void beforeRender(ds);
    Code:
       0: aload_0
       1: getstatic     #9                  // Field game:Lnet/minecraft/client/Minecraft;
       4: getfield      #17                 // Field net/minecraft/client/Minecraft.h:Ldc;
       7: invokestatic  #67                 // Method beforeRender:(Lds;Lgs;)V
      10: return

  public static void beforeRender(ds, gs);
    Code:
       0: getstatic     #68                 // Field com/unascribed/ears/common/debug/EarsLog$Tag.PLATFORM_INJECT_RENDERER:Lcom/unascribed/ears/common/debug/EarsLog$Tag;
       3: ldc           #69                 // String Before render rp={} player={}
       5: aload_0
       6: aload_1
       7: invokestatic  #28                 // Method com/unascribed/ears/common/debug/EarsLog.debug:(Lcom/unascribed/ears/common/debug/EarsLog$Tag;Ljava/lang/String;Ljava/lang/Object;Ljava/lang/Object;)V
      10: aload_1
      11: getfield      #70                 // Field gs.l:Ljava/lang/String;
      14: invokestatic  #71                 // Method com/unascribed/ears/legacy/LegacyHelper.isSlimArms:(Ljava/lang/String;)Z
      17: istore_2
      18: aload_0
      19: invokestatic  #72                 // Method getModelBipedMain:(Lds;)Lfh;
      22: astore_3
      23: iload_2
      24: ifeq          44
      27: aload_3
      28: getstatic     #73                 // Field slimLeftArm:Lps;
      31: putfield      #74                 // Field fh.e:Lps;
      34: aload_3
      35: getstatic     #75                 // Field slimRightArm:Lps;
      38: putfield      #76                 // Field fh.d:Lps;
      41: goto          58
      44: aload_3
      45: getstatic     #77                 // Field fatLeftArm:Lps;
      48: putfield      #74                 // Field fh.e:Lps;
      51: aload_3
      52: getstatic     #78                 // Field fatRightArm:Lps;
      55: putfield      #76                 // Field fh.d:Lps;
      58: return

  public static void checkSkin(java.lang.String, java.awt.image.BufferedImage);
    Code:
       0: getstatic     #19                 // Field com/unascribed/ears/common/debug/EarsLog$Tag.PLATFORM_INJECT:Lcom/unascribed/ears/common/debug/EarsLog$Tag;
       3: ldc           #79                 // String checkSkin({}, {})
       5: aload_0
       6: aload_1
       7: invokestatic  #28                 // Method com/unascribed/ears/common/debug/EarsLog.debug:(Lcom/unascribed/ears/common/debug/EarsLog$Tag;Ljava/lang/String;Ljava/lang/Object;Ljava/lang/Object;)V
      10: getstatic     #80                 // Field earsSkinFeatures:Ljava/util/Map;
      13: aload_0
      14: new           #23                 // class com/unascribed/ears/common/legacy/AWTEarsImage
      17: dup
      18: aload_1
      19: invokespecial #24                 // Method com/unascribed/ears/common/legacy/AWTEarsImage."<init>":(Ljava/awt/image/BufferedImage;)V
      22: aload_1
      23: getstatic     #22                 // Field com/unascribed/ears/common/util/EarsStorage$Key.ALFALFA:Lcom/unascribed/ears/common/util/EarsStorage$Key;
      26: invokestatic  #81                 // Method com/unascribed/ears/common/util/EarsStorage.get:(Ljava/lang/Object;Lcom/unascribed/ears/common/util/EarsStorage$Key;)Ljava/lang/Object;
      29: checkcast     #82                 // class com/unascribed/ears/api/features/AlfalfaData
      32: invokedynamic #83,  0             // InvokeDynamic #1:load:()Lcom/unascribed/ears/common/EarsFeaturesParser$PNGLoader;
      37: invokestatic  #84                 // Method com/unascribed/ears/common/EarsFeaturesParser.detect:(Lcom/unascribed/ears/common/EarsImage;Lcom/unascribed/ears/api/features/AlfalfaData;Lcom/unascribed/ears/common/EarsFeaturesParser$PNGLoader;)Lcom/unascribed/ears/api/features/EarsFeatures;
      40: invokeinterface #85,  3           // InterfaceMethod java/util/Map.put:(Ljava/lang/Object;Ljava/lang/Object;)Ljava/lang/Object;
      45: pop
      46: return

  public static java.lang.String amendSkinUrl(java.lang.String);
    Code:
       0: getstatic     #19                 // Field com/unascribed/ears/common/debug/EarsLog$Tag.PLATFORM_INJECT:Lcom/unascribed/ears/common/debug/EarsLog$Tag;
       3: ldc           #86                 // String Amend skin URL {}
       5: aload_0
       6: invokestatic  #87                 // Method com/unascribed/ears/common/debug/EarsLog.debug:(Lcom/unascribed/ears/common/debug/EarsLog$Tag;Ljava/lang/String;Ljava/lang/Object;)V
       9: aload_0
      10: ldc           #88                 // String https://betacraft.pl/skin/
      12: invokevirtual #89                 // Method java/lang/String.startsWith:(Ljava/lang/String;)Z
      15: ifeq          45
      18: aload_0
      19: ldc           #90                 // String .png
      21: invokevirtual #91                 // Method java/lang/String.endsWith:(Ljava/lang/String;)Z
      24: ifeq          45
      27: aload_0
      28: bipush        26
      30: aload_0
      31: invokevirtual #92                 // Method java/lang/String.length:()I
      34: iconst_4
      35: isub
      36: invokevirtual #93                 // Method java/lang/String.substring:(II)Ljava/lang/String;
      39: astore_1
      40: aload_1
      41: invokestatic  #94                 // Method com/unascribed/ears/legacy/LegacyHelper.getSkinUrl:(Ljava/lang/String;)Ljava/lang/String;
      44: areturn
      45: aload_0
      46: ldc           #95                 // String https://betacraft.uk/MinecraftSkins/
      48: invokevirtual #89                 // Method java/lang/String.startsWith:(Ljava/lang/String;)Z
      51: ifeq          81
      54: aload_0
      55: ldc           #90                 // String .png
      57: invokevirtual #91                 // Method java/lang/String.endsWith:(Ljava/lang/String;)Z
      60: ifeq          81
      63: aload_0
      64: bipush        36
      66: aload_0
      67: invokevirtual #92                 // Method java/lang/String.length:()I
      70: iconst_4
      71: isub
      72: invokevirtual #93                 // Method java/lang/String.substring:(II)Ljava/lang/String;
      75: astore_1
      76: aload_1
      77: invokestatic  #94                 // Method com/unascribed/ears/legacy/LegacyHelper.getSkinUrl:(Ljava/lang/String;)Ljava/lang/String;
      80: areturn
      81: aload_0
      82: ldc           #96                 // String http://s3.amazonaws.com/MinecraftSkins/
      84: invokevirtual #89                 // Method java/lang/String.startsWith:(Ljava/lang/String;)Z
      87: ifeq          117
      90: aload_0
      91: ldc           #90                 // String .png
      93: invokevirtual #91                 // Method java/lang/String.endsWith:(Ljava/lang/String;)Z
      96: ifeq          117
      99: aload_0
     100: bipush        39
     102: aload_0
     103: invokevirtual #92                 // Method java/lang/String.length:()I
     106: iconst_4
     107: isub
     108: invokevirtual #93                 // Method java/lang/String.substring:(II)Ljava/lang/String;
     111: astore_1
     112: aload_1
     113: invokestatic  #94                 // Method com/unascribed/ears/legacy/LegacyHelper.getSkinUrl:(Ljava/lang/String;)Ljava/lang/String;
     116: areturn
     117: aload_0
     118: areturn

  public static void amendTexturedQuad(tz, ib[], int, int, int, int);
    Code:
       0: getstatic     #97                 // Field forceTextureHeight:Z
       3: ifeq          133
       6: getstatic     #19                 // Field com/unascribed/ears/common/debug/EarsLog$Tag.PLATFORM_INJECT:Lcom/unascribed/ears/common/debug/EarsLog$Tag;
       9: ldc           #98                 // String amendTexturedQuad({}, ..., {}, {}, {}, {})
      11: aload_0
      12: iload_2
      13: iload_3
      14: iload         4
      16: iload         5
      18: invokestatic  #58                 // Method com/unascribed/ears/common/debug/EarsLog.debug:(Lcom/unascribed/ears/common/debug/EarsLog$Tag;Ljava/lang/String;Ljava/lang/Object;IIII)V
      21: ldc           #99                 // float 0.0015625f
      23: fstore        6
      25: ldc           #100                // float 0.003125f
      27: fstore        7
      29: aload_1
      30: iconst_0
      31: aload_1
      32: iconst_0
      33: aaload
      34: iload         4
      36: i2f
      37: ldc           #101                // float 64.0f
      39: fdiv
      40: fload         6
      42: fsub
      43: iload_3
      44: i2f
      45: ldc           #101                // float 64.0f
      47: fdiv
      48: fload         7
      50: fadd
      51: invokevirtual #102                // Method ib.a:(FF)Lib;
      54: aastore
      55: aload_1
      56: iconst_1
      57: aload_1
      58: iconst_1
      59: aaload
      60: iload_2
      61: i2f
      62: ldc           #101                // float 64.0f
      64: fdiv
      65: fload         6
      67: fadd
      68: iload_3
      69: i2f
      70: ldc           #101                // float 64.0f
      72: fdiv
      73: fload         7
      75: fadd
      76: invokevirtual #102                // Method ib.a:(FF)Lib;
      79: aastore
      80: aload_1
      81: iconst_2
      82: aload_1
      83: iconst_2
      84: aaload
      85: iload_2
      86: i2f
      87: ldc           #101                // float 64.0f
      89: fdiv
      90: fload         6
      92: fadd
      93: iload         5
      95: i2f
      96: ldc           #101                // float 64.0f
      98: fdiv
      99: fload         7
     101: fsub
     102: invokevirtual #102                // Method ib.a:(FF)Lib;
     105: aastore
     106: aload_1
     107: iconst_3
     108: aload_1
     109: iconst_3
     110: aaload
     111: iload         4
     113: i2f
     114: ldc           #101                // float 64.0f
     116: fdiv
     117: fload         6
     119: fsub
     120: iload         5
     122: i2f
     123: ldc           #101                // float 64.0f
     125: fdiv
     126: fload         7
     128: fsub
     129: invokevirtual #102                // Method ib.a:(FF)Lib;
     132: aastore
     133: return

  public static void amendPlayerRenderer(ds) throws java.lang.IllegalArgumentException, java.lang.IllegalAccessException;
    Code:
       0: getstatic     #11                 // Field com/unascribed/ears/common/debug/EarsLog$Tag.PLATFORM:Lcom/unascribed/ears/common/debug/EarsLog$Tag;
       3: ldc           #103                // String Hacking 64x64 skin support into player model
       5: invokestatic  #30                 // Method com/unascribed/ears/common/debug/EarsLog.debug:(Lcom/unascribed/ears/common/debug/EarsLog$Tag;Ljava/lang/String;)V
       8: iconst_1
       9: putstatic     #97                 // Field forceTextureHeight:Z
      12: new           #66                 // class fh
      15: dup
      16: fconst_0
      17: fconst_0
      18: invokespecial #104                // Method fh."<init>":(FF)V
      21: astore_1
      22: aload_1
      23: putstatic     #105                // Field myModel:Lfh;
      26: ldc           #106                // class gv
      28: invokevirtual #107                // Method java/lang/Class.getDeclaredFields:()[Ljava/lang/reflect/Field;
      31: iconst_0
      32: aaload
      33: astore_2
      34: aload_2
      35: iconst_1
      36: invokevirtual #108                // Method java/lang/reflect/Field.setAccessible:(Z)V
      39: aload_2
      40: aload_0
      41: aload_1
      42: invokevirtual #51                 // Method java/lang/reflect/Field.set:(Ljava/lang/Object;Ljava/lang/Object;)V
      45: aload_0
      46: aload_1
      47: invokestatic  #109                // Method setModelBipedMain:(Lds;Lfh;)V
      50: aload_1
      51: new           #110                // class com_unascribed_ears_ModelRendererTrans
      54: dup
      55: bipush        32
      57: iconst_0
      58: invokespecial #111                // Method com_unascribed_ears_ModelRendererTrans."<init>":(II)V
      61: putfield      #112                // Field fh.b:Lps;
      64: aload_1
      65: getfield      #112                // Field fh.b:Lps;
      68: ldc           #113                // float -4.0f
      70: ldc           #114                // float -8.0f
      72: ldc           #113                // float -4.0f
      74: bipush        8
      76: bipush        8
      78: bipush        8
      80: ldc           #115                // float 0.5f
      82: invokevirtual #116                // Method ps.a:(FFFIIIF)V
      85: aload_1
      86: getfield      #112                // Field fh.b:Lps;
      89: fconst_0
      90: fconst_0
      91: fconst_0
      92: invokevirtual #117                // Method ps.a:(FFF)V
      95: aload_1
      96: new           #118                // class ps
      99: dup
     100: bipush        32
     102: bipush        48
     104: invokespecial #119                // Method ps."<init>":(II)V
     107: putfield      #74                 // Field fh.e:Lps;
     110: aload_1
     111: getfield      #74                 // Field fh.e:Lps;
     114: ldc           #120                // float -1.0f
     116: ldc           #121                // float -2.0f
     118: ldc           #121                // float -2.0f
     120: iconst_4
     121: bipush        12
     123: iconst_4
     124: fconst_0
     125: invokevirtual #116                // Method ps.a:(FFFIIIF)V
     128: aload_1
     129: getfield      #74                 // Field fh.e:Lps;
     132: ldc           #122                // float 5.0f
     134: fconst_2
     135: fconst_0
     136: invokevirtual #117                // Method ps.a:(FFF)V
     139: aload_1
     140: new           #118                // class ps
     143: dup
     144: bipush        16
     146: bipush        48
     148: invokespecial #119                // Method ps."<init>":(II)V
     151: putfield      #123                // Field fh.g:Lps;
     154: aload_1
     155: getfield      #123                // Field fh.g:Lps;
     158: ldc           #121                // float -2.0f
     160: fconst_0
     161: ldc           #121                // float -2.0f
     163: iconst_4
     164: bipush        12
     166: iconst_4
     167: fconst_0
     168: invokevirtual #116                // Method ps.a:(FFFIIIF)V
     171: aload_1
     172: getfield      #123                // Field fh.g:Lps;
     175: ldc           #124                // float 1.9f
     177: ldc           #125                // float 12.0f
     179: fconst_0
     180: invokevirtual #117                // Method ps.a:(FFF)V
     183: aload_1
     184: getfield      #74                 // Field fh.e:Lps;
     187: putstatic     #77                 // Field fatLeftArm:Lps;
     190: aload_1
     191: getfield      #76                 // Field fh.d:Lps;
     194: putstatic     #78                 // Field fatRightArm:Lps;
     197: new           #118                // class ps
     200: dup
     201: bipush        32
     203: bipush        48
     205: invokespecial #119                // Method ps."<init>":(II)V
     208: putstatic     #73                 // Field slimLeftArm:Lps;
     211: getstatic     #73                 // Field slimLeftArm:Lps;
     214: ldc           #120                // float -1.0f
     216: ldc           #121                // float -2.0f
     218: ldc           #121                // float -2.0f
     220: iconst_3
     221: bipush        12
     223: iconst_4
     224: fconst_0
     225: invokevirtual #116                // Method ps.a:(FFFIIIF)V
     228: getstatic     #73                 // Field slimLeftArm:Lps;
     231: ldc           #122                // float 5.0f
     233: ldc           #126                // float 2.5f
     235: fconst_0
     236: invokevirtual #117                // Method ps.a:(FFF)V
     239: new           #118                // class ps
     242: dup
     243: bipush        40
     245: bipush        16
     247: invokespecial #119                // Method ps."<init>":(II)V
     250: putstatic     #75                 // Field slimRightArm:Lps;
     253: getstatic     #75                 // Field slimRightArm:Lps;
     256: ldc           #121                // float -2.0f
     258: ldc           #121                // float -2.0f
     260: ldc           #121                // float -2.0f
     262: iconst_3
     263: bipush        12
     265: iconst_4
     266: fconst_0
     267: invokevirtual #116                // Method ps.a:(FFFIIIF)V
     270: getstatic     #75                 // Field slimRightArm:Lps;
     273: ldc           #127                // float -5.0f
     275: ldc           #126                // float 2.5f
     277: fconst_0
     278: invokevirtual #117                // Method ps.a:(FFF)V
     281: aload_1
     282: getfield      #128                // Field fh.a:Lps;
     285: invokestatic  #129                // Method flipBottom:(Lps;)V
     288: aload_1
     289: getfield      #130                // Field fh.c:Lps;
     292: invokestatic  #129                // Method flipBottom:(Lps;)V
     295: getstatic     #77                 // Field fatLeftArm:Lps;
     298: invokestatic  #129                // Method flipBottom:(Lps;)V
     301: getstatic     #73                 // Field slimLeftArm:Lps;
     304: invokestatic  #129                // Method flipBottom:(Lps;)V
     307: getstatic     #78                 // Field fatRightArm:Lps;
     310: invokestatic  #129                // Method flipBottom:(Lps;)V
     313: getstatic     #75                 // Field slimRightArm:Lps;
     316: invokestatic  #129                // Method flipBottom:(Lps;)V
     319: aload_1
     320: getfield      #123                // Field fh.g:Lps;
     323: invokestatic  #129                // Method flipBottom:(Lps;)V
     326: aload_1
     327: getfield      #131                // Field fh.f:Lps;
     330: invokestatic  #129                // Method flipBottom:(Lps;)V
     333: aload_1
     334: getfield      #112                // Field fh.b:Lps;
     337: invokestatic  #129                // Method flipBottom:(Lps;)V
     340: iconst_0
     341: putstatic     #97                 // Field forceTextureHeight:Z
     344: return

  private static void flipBottom(ps) throws java.lang.IllegalArgumentException, java.lang.IllegalAccessException, java.lang.SecurityException;
    Code:
       0: ldc           #118                // class ps
       2: invokevirtual #107                // Method java/lang/Class.getDeclaredFields:()[Ljava/lang/reflect/Field;
       5: iconst_1
       6: aaload
       7: astore_1
       8: aload_1
       9: iconst_1
      10: invokevirtual #108                // Method java/lang/reflect/Field.setAccessible:(Z)V
      13: aload_1
      14: aload_0
      15: invokevirtual #63                 // Method java/lang/reflect/Field.get:(Ljava/lang/Object;)Ljava/lang/Object;
      18: checkcast     #132                // class "[Ltz;"
      21: astore_2
      22: aload_2
      23: iconst_3
      24: aaload
      25: getfield      #133                // Field tz.a:[Lib;
      28: astore_3
      29: aload_3
      30: iconst_0
      31: aaload
      32: getfield      #134                // Field ib.c:F
      35: fstore        4
      37: aload_3
      38: iconst_2
      39: aaload
      40: getfield      #134                // Field ib.c:F
      43: fstore        5
      45: aload_3
      46: iconst_0
      47: aaload
      48: fload         5
      50: putfield      #134                // Field ib.c:F
      53: aload_3
      54: iconst_1
      55: aaload
      56: fload         5
      58: putfield      #134                // Field ib.c:F
      61: aload_3
      62: iconst_2
      63: aaload
      64: fload         4
      66: putfield      #134                // Field ib.c:F
      69: aload_3
      70: iconst_3
      71: aaload
      72: fload         4
      74: putfield      #134                // Field ib.c:F
      77: return

  public void render(ds, gs, float);
    Code:
       0: getstatic     #135                // Field com/unascribed/ears/common/debug/EarsLog$Tag.PLATFORM_RENDERER:Lcom/unascribed/ears/common/debug/EarsLog$Tag;
       3: ldc           #136                // String render({}, {}, {})
       5: aload_2
       6: fconst_0
       7: fload_3
       8: invokestatic  #137                // Method com/unascribed/ears/common/debug/EarsLog.debug:(Lcom/unascribed/ears/common/debug/EarsLog$Tag;Ljava/lang/String;Ljava/lang/Object;FF)V
      11: aload_0
      12: aload_1
      13: putfield      #4                  // Field render:Lds;
      16: aload_0
      17: aload_2
      18: fload_3
      19: invokevirtual #138                // Method gs.a:(F)F
      22: putfield      #2                  // Field brightness:F
      25: aload_0
      26: fload_3
      27: putfield      #1                  // Field tickDelta:F
      30: aload_0
      31: getfield      #8                  // Field delegate:Lcom/unascribed/ears/common/legacy/ImmediateEarsRenderDelegate;
      34: aload_2
      35: invokevirtual #139                // Method com/unascribed/ears/common/legacy/ImmediateEarsRenderDelegate.render:(Ljava/lang/Object;)V
      38: aload_0
      39: aconst_null
      40: putfield      #4                  // Field render:Lds;
      43: return

  public void renderRightArm(ds, gs, float);
    Code:
       0: getstatic     #135                // Field com/unascribed/ears/common/debug/EarsLog$Tag.PLATFORM_RENDERER:Lcom/unascribed/ears/common/debug/EarsLog$Tag;
       3: ldc           #140                // String renderRightArm({}, {}, {})
       5: aload_1
       6: aload_2
       7: fload_3
       8: invokestatic  #141                // Method com/unascribed/ears/common/debug/EarsLog.debug:(Lcom/unascribed/ears/common/debug/EarsLog$Tag;Ljava/lang/String;Ljava/lang/Object;Ljava/lang/Object;F)V
      11: aload_0
      12: aload_1
      13: putfield      #4                  // Field render:Lds;
      16: aload_0
      17: aload_2
      18: fload_3
      19: invokevirtual #138                // Method gs.a:(F)F
      22: putfield      #2                  // Field brightness:F
      25: aload_0
      26: fload_3
      27: putfield      #1                  // Field tickDelta:F
      30: aload_0
      31: getfield      #8                  // Field delegate:Lcom/unascribed/ears/common/legacy/ImmediateEarsRenderDelegate;
      34: aload_2
      35: getstatic     #142                // Field com/unascribed/ears/common/render/EarsRenderDelegate$BodyPart.RIGHT_ARM:Lcom/unascribed/ears/common/render/EarsRenderDelegate$BodyPart;
      38: invokevirtual #143                // Method com/unascribed/ears/common/legacy/ImmediateEarsRenderDelegate.render:(Ljava/lang/Object;Lcom/unascribed/ears/common/render/EarsRenderDelegate$BodyPart;)V
      41: aload_0
      42: aconst_null
      43: putfield      #4                  // Field render:Lds;
      46: return

  private static com.unascribed.ears.common.EarsImage lambda$checkSkin$1(byte[]) throws java.io.IOException;
    Code:
       0: new           #23                 // class com/unascribed/ears/common/legacy/AWTEarsImage
       3: dup
       4: new           #144                // class java/io/ByteArrayInputStream
       7: dup
       8: aload_0
       9: invokespecial #145                // Method java/io/ByteArrayInputStream."<init>":([B)V
      12: invokestatic  #146                // Method javax/imageio/ImageIO.read:(Ljava/io/InputStream;)Ljava/awt/image/BufferedImage;
      15: invokespecial #24                 // Method com/unascribed/ears/common/legacy/AWTEarsImage."<init>":(Ljava/awt/image/BufferedImage;)V
      18: areturn

  private static void lambda$interceptParseUserSkin$0(rr, int, int, int, int);
    Code:
       0: aload_0
       1: iload_1
       2: iload_2
       3: iload_3
       4: iload         4
       6: invokestatic  #147                // Method setAreaOpaque:(Lrr;IIII)V
       9: return

  static ds access$000(com_unascribed_ears_Ears);
    Code:
       0: aload_0
       1: getfield      #4                  // Field render:Lds;
       4: areturn

  static ib[] access$100(ps);
    Code:
       0: aload_0
       1: invokestatic  #3                  // Method getVertices:(Lps;)[Lib;
       4: areturn

  static float access$200(com_unascribed_ears_Ears);
    Code:
       0: aload_0
       1: getfield      #2                  // Field brightness:F
       4: freturn

  static float access$300(com_unascribed_ears_Ears);
    Code:
       0: aload_0
       1: getfield      #1                  // Field tickDelta:F
       4: freturn

  static {};
    Code:
       0: new           #148                // class com_unascribed_ears_Ears
       3: dup
       4: invokespecial #149                // Method "<init>":()V
       7: putstatic     #15                 // Field INST:Lcom_unascribed_ears_Ears;
      10: new           #150                // class java/util/WeakHashMap
      13: dup
      14: invokespecial #151                // Method java/util/WeakHashMap."<init>":()V
      17: putstatic     #80                 // Field earsSkinFeatures:Ljava/util/Map;
      20: iconst_0
      21: putstatic     #152                // Field forceBipedTextureHeight:Z
      24: ldc           #153                // class rr
      26: ldc           #154                // String b
      28: iconst_4
      29: anewarray     #155                // class java/lang/Class
      32: dup
      33: iconst_0
      34: getstatic     #156                // Field java/lang/Integer.TYPE:Ljava/lang/Class;
      37: aastore
      38: dup
      39: iconst_1
      40: getstatic     #156                // Field java/lang/Integer.TYPE:Ljava/lang/Class;
      43: aastore
      44: dup
      45: iconst_2
      46: getstatic     #156                // Field java/lang/Integer.TYPE:Ljava/lang/Class;
      49: aastore
      50: dup
      51: iconst_3
      52: getstatic     #156                // Field java/lang/Integer.TYPE:Ljava/lang/Class;
      55: aastore
      56: invokevirtual #157                // Method java/lang/Class.getDeclaredMethod:(Ljava/lang/String;[Ljava/lang/Class;)Ljava/lang/reflect/Method;
      59: putstatic     #59                 // Field rr_setAreaOpaque:Ljava/lang/reflect/Method;
      62: getstatic     #59                 // Field rr_setAreaOpaque:Ljava/lang/reflect/Method;
      65: iconst_1
      66: invokevirtual #158                // Method java/lang/reflect/Method.setAccessible:(Z)V
      69: ldc           #153                // class rr
      71: ldc           #159                // String a
      73: iconst_4
      74: anewarray     #155                // class java/lang/Class
      77: dup
      78: iconst_0
      79: getstatic     #156                // Field java/lang/Integer.TYPE:Ljava/lang/Class;
      82: aastore
      83: dup
      84: iconst_1
      85: getstatic     #156                // Field java/lang/Integer.TYPE:Ljava/lang/Class;
      88: aastore
      89: dup
      90: iconst_2
      91: getstatic     #156                // Field java/lang/Integer.TYPE:Ljava/lang/Class;
      94: aastore
      95: dup
      96: iconst_3
      97: getstatic     #156                // Field java/lang/Integer.TYPE:Ljava/lang/Class;
     100: aastore
     101: invokevirtual #157                // Method java/lang/Class.getDeclaredMethod:(Ljava/lang/String;[Ljava/lang/Class;)Ljava/lang/reflect/Method;
     104: putstatic     #61                 // Field rr_setAreaTransparent:Ljava/lang/reflect/Method;
     107: getstatic     #61                 // Field rr_setAreaTransparent:Ljava/lang/reflect/Method;
     110: iconst_1
     111: invokevirtual #158                // Method java/lang/reflect/Method.setAccessible:(Z)V
     114: ldc           #153                // class rr
     116: ldc           #160                // String c
     118: invokevirtual #161                // Method java/lang/Class.getDeclaredField:(Ljava/lang/String;)Ljava/lang/reflect/Field;
     121: putstatic     #55                 // Field rr_imageHeight:Ljava/lang/reflect/Field;
     124: getstatic     #55                 // Field rr_imageHeight:Ljava/lang/reflect/Field;
     127: iconst_1
     128: invokevirtual #108                // Method java/lang/reflect/Field.setAccessible:(Z)V
     131: ldc           #153                // class rr
     133: ldc           #154                // String b
     135: invokevirtual #161                // Method java/lang/Class.getDeclaredField:(Ljava/lang/String;)Ljava/lang/reflect/Field;
     138: putstatic     #49                 // Field rr_imageWidth:Ljava/lang/reflect/Field;
     141: getstatic     #49                 // Field rr_imageWidth:Ljava/lang/reflect/Field;
     144: iconst_1
     145: invokevirtual #108                // Method java/lang/reflect/Field.setAccessible:(Z)V
     148: ldc           #153                // class rr
     150: ldc           #159                // String a
     152: invokevirtual #161                // Method java/lang/Class.getDeclaredField:(Ljava/lang/String;)Ljava/lang/reflect/Field;
     155: putstatic     #56                 // Field rr_imageData:Ljava/lang/reflect/Field;
     158: getstatic     #56                 // Field rr_imageData:Ljava/lang/reflect/Field;
     161: iconst_1
     162: invokevirtual #108                // Method java/lang/reflect/Field.setAccessible:(Z)V
     165: ldc           #118                // class ps
     167: ldc           #162                // String j
     169: invokevirtual #161                // Method java/lang/Class.getDeclaredField:(Ljava/lang/String;)Ljava/lang/reflect/Field;
     172: putstatic     #62                 // Field ps_vertices:Ljava/lang/reflect/Field;
     175: getstatic     #62                 // Field ps_vertices:Ljava/lang/reflect/Field;
     178: iconst_1
     179: invokevirtual #108                // Method java/lang/reflect/Field.setAccessible:(Z)V
     182: ldc           #163                // class ds
     184: ldc           #159                // String a
     186: invokevirtual #161                // Method java/lang/Class.getDeclaredField:(Ljava/lang/String;)Ljava/lang/reflect/Field;
     189: putstatic     #65                 // Field ds_modelBipedMain:Ljava/lang/reflect/Field;
     192: getstatic     #65                 // Field ds_modelBipedMain:Ljava/lang/reflect/Field;
     195: iconst_1
     196: invokevirtual #108                // Method java/lang/reflect/Field.setAccessible:(Z)V
     199: goto          212
     202: astore_0
     203: new           #53                 // class java/lang/RuntimeException
     206: dup
     207: aload_0
     208: invokespecial #54                 // Method java/lang/RuntimeException."<init>":(Ljava/lang/Throwable;)V
     211: athrow
     212: return
    Exception table:
       from    to  target type
          24   199   202   Class java/lang/Throwable
}
